.DS_Store
s4d/.DS_Store
s4d/__init__.py
s4d/diar.py
s4d/diar_tools.py
s4d/features_server.py
s4d/model_iv.py
s4d/scoring.py
s4d/segmentation.py
s4d/utils.py
s4d/viterbi.py
s4d/alien/__init__.py
s4d/alien/hmm.py
s4d/alien/mixture.py
s4d/clustering/__init__.py
s4d/clustering/cc_iv.py
s4d/clustering/gauss.py
s4d/clustering/hac_bic.py
s4d/clustering/hac_clr.py
s4d/clustering/hac_iv.py
s4d/clustering/hac_utils.py
s4d/clustering/ilp_iv.py
s4d/gui/__init__.py
s4d/gui/dendrogram.py
s4d/gui/player.py
s4d/gui/viewer.py
s4d/gui/viewer_utils.py
s4d-0.0.4.1.dist-info/METADATA
s4d-0.0.4.1.dist-info/RECORD
s4d-0.0.4.1.dist-info/WHEEL
s4d-0.0.4.1.dist-info/top_level.txt
