Metadata-Version: 2.1
Name: s4d
Version: 0.0.4.1
Summary: S4D: SIDEKIT for Diarization
Home-page: https://projets-lium.univ-lemans.fr/s4d/
Author: Sylvain MEIGNIER
Author-email: s4d@univ-lemans.fr
License: UNKNOWN
Platform: UNKNOWN
Classifier: Programming Language :: Python :: 3
Classifier: License :: OSI Approved :: GNU Library or Lesser General Public License (LGPL)
Classifier: Operating System :: OS Independent
Classifier: Development Status :: 5 - Production/Stable
Classifier: Topic :: Scientific/Engineering
